pydantic_sarif/__init__.py
pydantic_sarif/model.py
pydantic_sarif-0.1.1.dist-info/METADATA
pydantic_sarif-0.1.1.dist-info/WHEEL
pydantic_sarif-0.1.1.dist-info/RECORD
